jinja2_context_filters/__init__.py
jinja2_context_filters-1.0.0.dist-info/LICENSE
jinja2_context_filters-1.0.0.dist-info/METADATA
jinja2_context_filters-1.0.0.dist-info/WHEEL
jinja2_context_filters-1.0.0.dist-info/top_level.txt
jinja2_context_filters-1.0.0.dist-info/RECORD
