Metadata-Version: 2.1
Name: jinja2-context-filters
Version: 1.0.0
Summary: Jinja2 filters to expose Context and Environment values to templates.
Home-page: UNKNOWN
Author: Nick Shobe
Author-email: nickshobe@gmail.com
License: MIT License
Platform: UNKNOWN
Requires-Dist: Jinja2
Provides-Extra: test
Requires-Dist: pytest ; extra == 'test'
Requires-Dist: pytest-cov ; extra == 'test'
